cdo_sdk_python/__init__.py
cdo_sdk_python/api_client.py
cdo_sdk_python/api_response.py
cdo_sdk_python/configuration.py
cdo_sdk_python/exceptions.py
cdo_sdk_python/py.typed
cdo_sdk_python/rest.py
cdo_sdk_python/api/__init__.py
cdo_sdk_python/api/access_groups_api.py
cdo_sdk_python/api/ai_assistant_api.py
cdo_sdk_python/api/asa_access_rules_api.py
cdo_sdk_python/api/audit_logs_api.py
cdo_sdk_python/api/change_requests_api.py
cdo_sdk_python/api/changelogs_api.py
cdo_sdk_python/api/cloud_delivered_fmc_api.py
cdo_sdk_python/api/command_line_interface_api.py
cdo_sdk_python/api/commands_api.py
cdo_sdk_python/api/connectors_api.py
cdo_sdk_python/api/device_upgrades_api.py
cdo_sdk_python/api/inventory_api.py
cdo_sdk_python/api/meta_api.py
cdo_sdk_python/api/msp_api.py
cdo_sdk_python/api/object_management_api.py
cdo_sdk_python/api/remote_access_monitoring_api.py
cdo_sdk_python/api/search_api.py
cdo_sdk_python/api/swagger_redirect_controller_api.py
cdo_sdk_python/api/tenant_management_api.py
cdo_sdk_python/api/transactions_api.py
cdo_sdk_python/api/users_api.py
cdo_sdk_python/models/__init__.py
cdo_sdk_python/models/access_group.py
cdo_sdk_python/models/access_group_create_input.py
cdo_sdk_python/models/access_group_page.py
cdo_sdk_python/models/access_group_update_input.py
cdo_sdk_python/models/access_rule.py
cdo_sdk_python/models/access_rule_create_input.py
cdo_sdk_python/models/access_rule_details_content.py
cdo_sdk_python/models/access_rule_issue.py
cdo_sdk_python/models/access_rule_page.py
cdo_sdk_python/models/access_rule_update_input.py
cdo_sdk_python/models/active_directory_group.py
cdo_sdk_python/models/active_directory_group_create_or_update_input.py
cdo_sdk_python/models/active_directory_group_page.py
cdo_sdk_python/models/ai_assistant_conversation_page.py
cdo_sdk_python/models/ai_conversation.py
cdo_sdk_python/models/ai_message.py
cdo_sdk_python/models/ai_question.py
cdo_sdk_python/models/api_token_info.py
cdo_sdk_python/models/application_context.py
cdo_sdk_python-1.9.85.dist-info/METADATA
cdo_sdk_python-1.9.85.dist-info/WHEEL
cdo_sdk_python-1.9.85.dist-info/top_level.txt
cdo_sdk_python-1.9.85.dist-info/RECORD
