Metadata-Version: 2.1
Name: cdo-sdk-python
Version: 1.9.85
Summary: Cisco Security Cloud Control API
Home-page: 
Author: Cisco Security Cloud Control TAC
Author-email: cdo.tac@cisco.com
Keywords: OpenAPI,OpenAPI-Generator,Cisco Security Cloud Control API
Requires-Dist: pydantic (>=2)
Requires-Dist: python-dateutil
Requires-Dist: typing-extensions (>=4.7.1)
Requires-Dist: urllib3 (<2.1.0,>=1.25.3)
